<annotation>
	<folder>Surprise</folder>
	<filename>Surprise 37.jpg</filename>
	<path>C:\Users\Juan\Desktop\TFG\Entrenamiento\Emociones\train\Surprise\Surprise 37.jpg</path>
	<source>
		<database>Unknown</database>
	</source>
	<size>
		<width>255</width>
		<height>198</height>
		<depth>3</depth>
	</size>
	<segmented>0</segmented>
	<object>
		<name>Surprise</name>
		<pose>Unspecified</pose>
		<truncated>0</truncated>
		<difficult>0</difficult>
		<bndbox>
			<xmin>51</xmin>
			<ymin>25</ymin>
			<xmax>93</xmax>
			<ymax>83</ymax>
		</bndbox>
	</object>
</annotation>
